<?xml version="1.0" encoding="UTF-8" standalone="yes"?>
<p:sld xmlns:a="http://schemas.openxmlformats.org/drawingml/2006/main" xmlns:r="http://schemas.openxmlformats.org/officeDocument/2006/relationships" xmlns:p="http://schemas.openxmlformats.org/presentationml/2006/main"><p:cSld><p:spTree><p:nvGrpSpPr><p:cNvPr id="1" name="Shape 229"/><p:cNvGrpSpPr/><p:nvPr/></p:nvGrpSpPr><p:grpSpPr><a:xfrm><a:off x="0" y="0"/><a:ext cx="0" cy="0"/><a:chOff x="0" y="0"/><a:chExt cx="0" cy="0"/></a:xfrm></p:grpSpPr><p:graphicFrame><p:nvGraphicFramePr><p:cNvPr id="11" name="資料庫圖表 10"><a:extLst><a:ext uri="{FF2B5EF4-FFF2-40B4-BE49-F238E27FC236}"><a16:creationId xmlns:a16="http://schemas.microsoft.com/office/drawing/2014/main" id="{E7781766-DC46-4E80-901D-704AC819FB56}"/></a:ext></a:extLst></p:cNvPr><p:cNvGraphicFramePr/><p:nvPr/></p:nvGraphicFramePr><p:xfrm><a:off x="-32" y="4431203"/><a:ext cx="9144000" cy="756843"/></p:xfrm><a:graphic><a:graphicData uri="http://schemas.openxmlformats.org/drawingml/2006/diagram"><dgm:relIds xmlns:dgm="http://schemas.openxmlformats.org/drawingml/2006/diagram" xmlns:r="http://schemas.openxmlformats.org/officeDocument/2006/relationships" r:dm="rId3" r:lo="rId4" r:qs="rId5" r:cs="rId6"/></a:graphicData></a:graphic></p:graphicFrame><p:sp><p:nvSpPr><p:cNvPr id="16" name="CustomShape 6"><a:extLst><a:ext uri="{FF2B5EF4-FFF2-40B4-BE49-F238E27FC236}"><a16:creationId xmlns:a16="http://schemas.microsoft.com/office/drawing/2014/main" id="{BA20F6CD-C7A0-430E-AFF3-321172BE19F7}"/></a:ext></a:extLst></p:cNvPr><p:cNvSpPr/><p:nvPr/></p:nvSpPr><p:spPr><a:xfrm rot="16200000"><a:off x="3895876" y="1930911"/><a:ext cx="520200" cy="799200"/></a:xfrm><a:prstGeom prst="downArrow"><a:avLst><a:gd name="adj1" fmla="val 50000"/><a:gd name="adj2" fmla="val 50000"/></a:avLst></a:prstGeom></p:spPr><p:style><a:lnRef idx="2"><a:schemeClr val="accent6"><a:shade val="50000"/></a:schemeClr></a:lnRef><a:fillRef idx="1"><a:schemeClr val="accent6"/></a:fillRef><a:effectRef idx="0"><a:schemeClr val="accent6"/></a:effectRef><a:fontRef idx="minor"><a:schemeClr val="lt1"/></a:fontRef></p:style></p:sp><p:pic><p:nvPicPr><p:cNvPr id="15" name="圖片 14"><a:extLst><a:ext uri="{FF2B5EF4-FFF2-40B4-BE49-F238E27FC236}"><a16:creationId xmlns:a16="http://schemas.microsoft.com/office/drawing/2014/main" id="{97B2D680-0690-47B6-85B0-4DE42F564064}"/></a:ext></a:extLst></p:cNvPr><p:cNvPicPr><a:picLocks noChangeAspect="1"/></p:cNvPicPr><p:nvPr/></p:nvPicPr><p:blipFill rotWithShape="1"><a:blip r:embed="rId8"/><a:srcRect l="2768" t="2225" r="2768" b="4457"/><a:stretch/></p:blipFill><p:spPr><a:xfrm><a:off x="1006609" y="1261033"/><a:ext cx="2583246" cy="2314192"/></a:xfrm><a:prstGeom prst="roundRect"><a:avLst><a:gd name="adj" fmla="val 8594"/></a:avLst></a:prstGeom><a:solidFill><a:srgbClr val="FFFFFF"><a:shade val="85000"/></a:srgbClr></a:solidFill><a:ln w="12700"><a:solidFill><a:srgbClr val="39996E"/></a:solidFill></a:ln><a:effectLst/></p:spPr></p:pic><p:pic><p:nvPicPr><p:cNvPr id="17" name="圖片 16"><a:extLst><a:ext uri="{FF2B5EF4-FFF2-40B4-BE49-F238E27FC236}"><a16:creationId xmlns:a16="http://schemas.microsoft.com/office/drawing/2014/main" id="{832B300F-FAE5-4460-AACE-8DCA7C25661C}"/></a:ext></a:extLst></p:cNvPr><p:cNvPicPr><a:picLocks noChangeAspect="1"/></p:cNvPicPr><p:nvPr/></p:nvPicPr><p:blipFill><a:blip r:embed="rId9"/><a:stretch><a:fillRect/></a:stretch></p:blipFill><p:spPr><a:xfrm rot="21198334"><a:off x="2717625" y="2987090"/><a:ext cx="751552" cy="751550"/></a:xfrm><a:prstGeom prst="rect"><a:avLst/></a:prstGeom></p:spPr></p:pic><p:sp><p:nvSpPr><p:cNvPr id="12" name="文字方塊 11"><a:extLst><a:ext uri="{FF2B5EF4-FFF2-40B4-BE49-F238E27FC236}"><a16:creationId xmlns:a16="http://schemas.microsoft.com/office/drawing/2014/main" id="{BA882B51-E0E4-4003-8E84-9F6D587093D7}"/></a:ext></a:extLst></p:cNvPr><p:cNvSpPr txBox="1"/><p:nvPr/></p:nvSpPr><p:spPr><a:xfrm><a:off x="4722097" y="2172083"/><a:ext cx="3423237" cy="369332"/></a:xfrm><a:prstGeom prst="rect"><a:avLst/></a:prstGeom><a:noFill/></p:spPr><p:txBody><a:bodyPr wrap="square"><a:spAutoFit/></a:bodyPr><a:lstStyle/><a:p><a:pPr marL="0" marR="0" lvl="0" indent="0" defTabSz="914400" rtl="0" eaLnBrk="1" fontAlgn="auto" latinLnBrk="0" hangingPunct="1"><a:lnSpc><a:spcPct val="100000"/></a:lnSpc><a:spcBef><a:spcPts val="0"/></a:spcBef><a:spcAft><a:spcPts val="1200"/></a:spcAft><a:buClr><a:srgbClr val="000000"/></a:buClr><a:buSzTx/><a:buFont typeface="Arial"/><a:buNone/><a:tabLst/><a:defRPr/></a:pPr><a:r><a:rPr kumimoji="0" lang="zh-TW" altLang="en-US" sz="1800" b="1" i="0" u="sng" strike="noStrike" kern="0" cap="none" spc="0" normalizeH="0" baseline="0" noProof="0" dirty="0"><a:ln><a:noFill/></a:ln><a:solidFill><a:srgbClr val="FFC167"><a:lumMod val="50000"/></a:srgbClr></a:solidFill><a:effectLst/><a:uLnTx/><a:uFillTx/><a:latin typeface="Arial"/><a:cs typeface="Arial"/><a:sym typeface="Arial"/></a:rPr><a:t>針對各空品質指標進行好物推薦</a:t></a:r><a:endParaRPr kumimoji="0" lang="en-US" altLang="zh-TW" sz="1800" b="1" i="0" u="sng" strike="noStrike" kern="0" cap="none" spc="0" normalizeH="0" baseline="0" noProof="0" dirty="0"><a:ln><a:noFill/></a:ln><a:solidFill><a:srgbClr val="FFC167"><a:lumMod val="50000"/></a:srgbClr></a:solidFill><a:effectLst/><a:uLnTx/><a:uFillTx/><a:latin typeface="Arial"/><a:cs typeface="Arial"/><a:sym typeface="Arial"/></a:endParaRPr></a:p></p:txBody></p:sp><p:sp><p:nvSpPr><p:cNvPr id="3" name="投影片編號版面配置區 2"><a:extLst><a:ext uri="{FF2B5EF4-FFF2-40B4-BE49-F238E27FC236}"><a16:creationId xmlns:a16="http://schemas.microsoft.com/office/drawing/2014/main" id="{B19DCCDB-75D1-442F-B4E6-B2516C1B0AE2}"/></a:ext></a:extLst></p:cNvPr><p:cNvSpPr><a:spLocks noGrp="1"/></p:cNvSpPr><p:nvPr><p:ph type="sldNum" idx="12"/></p:nvPr></p:nvSpPr><p:spPr/><p:txBody><a:bodyPr/><a:lstStyle/><a:p><a:pPr marL="0" lvl="0" indent="0" algn="r" rtl="0"><a:spcBef><a:spcPts val="0"/></a:spcBef><a:spcAft><a:spcPts val="0"/></a:spcAft><a:buNone/></a:pPr><a:fld id="{00000000-1234-1234-1234-123412341234}" type="slidenum"><a:rPr lang="en" smtClean="0"/><a:t>17</a:t></a:fld><a:endParaRPr lang="en" dirty="0"/></a:p></p:txBody></p:sp><p:grpSp><p:nvGrpSpPr><p:cNvPr id="13" name="群組 12"><a:extLst><a:ext uri="{FF2B5EF4-FFF2-40B4-BE49-F238E27FC236}"><a16:creationId xmlns:a16="http://schemas.microsoft.com/office/drawing/2014/main" id="{8C47C7B9-F275-4710-97A3-E50DB5198E06}"/></a:ext></a:extLst></p:cNvPr><p:cNvGrpSpPr/><p:nvPr/></p:nvGrpSpPr><p:grpSpPr><a:xfrm><a:off x="7123099" y="3"/><a:ext cx="2020892" cy="1014289"/><a:chOff x="7123099" y="3"/><a:chExt cx="2020892" cy="1014289"/></a:xfrm></p:grpSpPr><p:sp><p:nvSpPr><p:cNvPr id="14" name="Google Shape;232;p37"><a:extLst><a:ext uri="{FF2B5EF4-FFF2-40B4-BE49-F238E27FC236}"><a16:creationId xmlns:a16="http://schemas.microsoft.com/office/drawing/2014/main" id="{D9478EC5-335C-4E3E-B843-C20B406C1117}"/></a:ext></a:extLst></p:cNvPr><p:cNvSpPr/><p:nvPr/></p:nvSpPr><p:spPr><a:xfrm rot="16200000" flipH="1"><a:off x="7626400" y="-503298"/><a:ext cx="1014289" cy="2020892"/></a:xfrm><a:custGeom><a:avLst/><a:gdLst/><a:ahLst/><a:cxnLst/><a:rect l="l" t="t" r="r" b="b"/><a:pathLst><a:path w="41960" h="51451" extrusionOk="0"><a:moveTo><a:pt x="6508" y="1"/></a:moveTo><a:cubicBezTo><a:pt x="4266" y="1"/><a:pt x="2074" y="345"/><a:pt x="1" y="1022"/></a:cubicBezTo><a:lnTo><a:pt x="1" y="51451"/></a:lnTo><a:lnTo><a:pt x="27365" y="51451"/></a:lnTo><a:cubicBezTo><a:pt x="28929" y="50408"/><a:pt x="30362" y="48975"/><a:pt x="31858" y="47150"/></a:cubicBezTo><a:cubicBezTo><a:pt x="41960" y="34250"/><a:pt x="29581" y="14052"/><a:pt x="29581" y="14052"/></a:cubicBezTo><a:cubicBezTo><a:pt x="23402" y="4508"/><a:pt x="14624" y="1"/><a:pt x="6508" y="1"/></a:cubicBezTo><a:close/></a:path></a:pathLst></a:custGeom><a:solidFill><a:schemeClr val="accent5"/></a:solidFill><a:ln><a:noFill/></a:ln></p:spPr><p:txBody><a:bodyPr spcFirstLastPara="1" wrap="square" lIns="91425" tIns="91425" rIns="91425" bIns="91425" anchor="ctr" anchorCtr="0"><a:noAutofit/></a:bodyPr><a:lstStyle/><a:p><a:pPr marL="0" lvl="0" indent="0" algn="l" rtl="0"><a:spcBef><a:spcPts val="0"/></a:spcBef><a:spcAft><a:spcPts val="0"/></a:spcAft><a:buNone/></a:pPr><a:endParaRPr/></a:p></p:txBody></p:sp><p:sp><p:nvSpPr><p:cNvPr id="18" name="文字方塊 17"><a:extLst><a:ext uri="{FF2B5EF4-FFF2-40B4-BE49-F238E27FC236}"><a16:creationId xmlns:a16="http://schemas.microsoft.com/office/drawing/2014/main" id="{D2DEF76A-F654-418F-9A6A-BCEE90DF84C4}"/></a:ext></a:extLst></p:cNvPr><p:cNvSpPr txBox="1"/><p:nvPr/></p:nvSpPr><p:spPr><a:xfrm><a:off x="7457709" y="172007"/><a:ext cx="1686282" cy="338554"/></a:xfrm><a:prstGeom prst="rect"><a:avLst/></a:prstGeom><a:noFill/></p:spPr><p:txBody><a:bodyPr wrap="square"><a:spAutoFit/></a:bodyPr><a:lstStyle/><a:p><a:pPr marL="0" lvl="0" indent="0" algn="l" rtl="0"><a:spcBef><a:spcPts val="0"/></a:spcBef><a:spcAft><a:spcPts val="0"/></a:spcAft><a:buNone/></a:pPr><a:r><a:rPr lang="zh-TW" altLang="en-US" sz="1600" b="1" dirty="0"><a:solidFill><a:schemeClr val="bg1"/></a:solidFill></a:rPr><a:t>報告人：劉佩萱</a:t></a:r></a:p></p:txBody></p:sp></p:grpSp></p:spTree><p:extLst><p:ext uri="{BB962C8B-B14F-4D97-AF65-F5344CB8AC3E}"><p14:creationId xmlns:p14="http://schemas.microsoft.com/office/powerpoint/2010/main" val="4238961894"/></p:ext></p:extLst></p:cSld><p:clrMapOvr><a:masterClrMapping/></p:clrMapOvr></p:sld>